monopoly/__init__.py
monopoly/banks/__init__.py
monopoly/banks/amex/__init__.py
monopoly/banks/amex/amex.py
monopoly/banks/bank_of_america/__init__.py
monopoly/banks/bank_of_america/boa.py
monopoly/banks/base.py
monopoly/banks/bmo/__init__.py
monopoly/banks/bmo/bmo.py
monopoly/banks/canadian_tire/__init__.py
monopoly/banks/canadian_tire/canadian_tire.py
monopoly/banks/capitalone/__init__.py
monopoly/banks/capitalone/capitalone.py
monopoly/banks/chase/__init__.py
monopoly/banks/chase/chase.py
monopoly/banks/cibc/__init__.py
monopoly/banks/cibc/cibc.py
monopoly/banks/citibank/__init__.py
monopoly/banks/citibank/citibank.py
monopoly/banks/dbs/__init__.py
monopoly/banks/dbs/dbs.py
monopoly/banks/detector.py
monopoly/banks/example_bank.py
monopoly/banks/hsbc/__init__.py
monopoly/banks/hsbc/hsbc.py
monopoly/banks/maybank/__init__.py
monopoly/banks/maybank/maybank.py
monopoly/banks/ocbc/__init__.py
monopoly/banks/ocbc/ocbc.py
monopoly/banks/rbc/__init__.py
monopoly/banks/rbc/rbc.py
monopoly/banks/scotiabank/__init__.py
monopoly/banks/scotiabank/scotiabank.py
monopoly/banks/standard_chartered/__init__.py
monopoly/banks/standard_chartered/standard_chartered.py
monopoly/banks/td_canada_trust/__init__.py
monopoly/banks/td_canada_trust/tdct.py
monopoly/banks/trust/__init__.py
monopoly/banks/trust/trust.py
monopoly/banks/uob/__init__.py
monopoly/banks/uob/uob.py
monopoly/banks/zkb/__init__.py
monopoly/banks/zkb/zkb.py
monopoly/cli/__init__.py
monopoly/cli/cli.py
monopoly/cli/models.py
monopoly/config.py
monopoly/constants/__init__.py
monopoly/constants/date.py
monopoly/constants/statement.py
monopoly/enums.py
monopoly/examples/__init__.py
monopoly/examples/example_statement.pdf
monopoly/examples/single_statement.py
monopoly/generic/__init__.py
monopoly/generic/generic.py
monopoly/generic/handler.py
monopoly/generic/patterns.py
monopoly/handler.py
monopoly/identifiers.py
monopoly/log.py
monopoly/pdf.py
monopoly/pipeline.py
monopoly/statements/__init__.py
monopoly_core-0.19.7.dist-info/METADATA
monopoly_core-0.19.7.dist-info/WHEEL
monopoly_core-0.19.7.dist-info/entry_points.txt
monopoly_core-0.19.7.dist-info/licenses/LICENSE.md
monopoly_core-0.19.7.dist-info/RECORD
