Metadata-Version: 2.1
Name: monopoly-core
Version: 0.19.7
Summary: Monopoly is a Python library & CLI that converts bank statement PDFs to CSV
Author-Email: benjamin-awd <benjamindornel@gmail.com>
License: AGPL-3.0
Classifier: Development Status :: 3 - Alpha
Classifier: Programming Language :: Python :: 3.10
Classifier: Programming Language :: Python :: 3.11
Classifier: Programming Language :: Python :: 3.12
Classifier: Programming Language :: Python :: 3.13
Project-URL: repository, https://github.com/benjamin-awd/monopoly
Requires-Python: <3.14,>=3.10
Requires-Dist: pydantic-settings>=2.9.1
Requires-Dist: pymupdf>=1.26.0
Requires-Dist: pdftotext>=3.0.0
Requires-Dist: click>=8.2.1
Requires-Dist: tqdm>=4.67.1
Requires-Dist: tabulate>=0.9.0
Requires-Dist: pydantic>=2.11.5
Requires-Dist: dateparser>=1.2.1
Requires-Dist: strenum>=0.4.15
Provides-Extra: ocr
Requires-Dist: ocrmypdf<17.0.0,>=16.5.0; extra == "ocr"
